{
  "resourceType": "Observation",
  "id": "ancillary-egfr-present",
  "meta": {
    "profile": [
      "http://canshare.com/fhir/StructureDefinition/observation-egfr"
    ]
  },
  "code": {
    "coding": [
      {
        "code": "1111",
        "system": "http://snomed.info/sct",
        "display": "EGFR"
      }
    ]
  },
  "text": {
    "div": "<div xmlns=\"http://www.w3.org/1999/xhtml\">EGFR present</div>",
    "status": "generated"
  },
  "status": "final",
  "subject": {
    "reference": "Patient/johndoe"
  },
  "valueCodeableConcept": {
    "coding": [
      {
        "code": "present",
        "system": "http://canshare.com/fhir/CodeSystem/cs-egfr"
      }
    ]
  }
}
